interpres-0.4.0b6.dist-info/licenses/LICENSE
translator/__init__.py
translator/__main__.py
translator/language.py
translator/main.py
translator/translate.py
translator/utils.py
interpres-0.4.0b6.dist-info/METADATA
interpres-0.4.0b6.dist-info/WHEEL
interpres-0.4.0b6.dist-info/entry_points.txt
interpres-0.4.0b6.dist-info/top_level.txt
interpres-0.4.0b6.dist-info/RECORD
