Metadata-Version: 2.4
Name: interpres
Version: 0.4.0b6
Summary: Translate from one language to another.
Home-page: https://github.com/wasertech/Translator
Author: Danny Waser
License: LICENSE
Project-URL: Documentation, https://github.com/wasertech/Translator/blob/main/README.md
Project-URL: Code, https://github.com/wasertech/Translator
Project-URL: Issue tracker, https://github.com/wasertech/Translator/issues
Classifier: Programming Language :: Python :: 3
Classifier: Programming Language :: Python :: 3.8
Classifier: Programming Language :: Python :: 3.9
Classifier: Programming Language :: Python :: 3.10
Classifier: License :: OSI Approved :: Mozilla Public License 2.0 (MPL 2.0)
Classifier: Operating System :: OS Independent
Classifier: Topic :: Text Processing
Classifier: Topic :: Terminals
Classifier: Topic :: System :: Shells
Classifier: Programming Language :: Unix Shell
Classifier: Natural Language :: Afrikaans
Classifier: Natural Language :: Arabic
Classifier: Natural Language :: Basque
Classifier: Natural Language :: Bengali
Classifier: Natural Language :: Bosnian
Classifier: Natural Language :: Bulgarian
Classifier: Natural Language :: Cantonese
Classifier: Natural Language :: Catalan
Classifier: Natural Language :: Chinese (Simplified)
Classifier: Natural Language :: Chinese (Traditional)
Classifier: Natural Language :: Croatian
Classifier: Natural Language :: Czech
Classifier: Natural Language :: Danish
Classifier: Natural Language :: Dutch
Classifier: Natural Language :: English
Classifier: Natural Language :: Esperanto
Classifier: Natural Language :: Finnish
Classifier: Natural Language :: French
Classifier: Natural Language :: Galician
Classifier: Natural Language :: German
Classifier: Natural Language :: Greek
Classifier: Natural Language :: Hebrew
Classifier: Natural Language :: Hindi
Classifier: Natural Language :: Hungarian
Classifier: Natural Language :: Icelandic
Classifier: Natural Language :: Indonesian
Classifier: Natural Language :: Irish
Classifier: Natural Language :: Italian
Classifier: Natural Language :: Japanese
Classifier: Natural Language :: Javanese
Classifier: Natural Language :: Korean
Classifier: Natural Language :: Latin
Classifier: Natural Language :: Latvian
Classifier: Natural Language :: Lithuanian
Classifier: Natural Language :: Macedonian
Classifier: Natural Language :: Malay
Classifier: Natural Language :: Marathi
Classifier: Natural Language :: Nepali
Classifier: Natural Language :: Norwegian
Classifier: Natural Language :: Panjabi
Classifier: Natural Language :: Persian
Classifier: Natural Language :: Polish
Classifier: Natural Language :: Portuguese
Classifier: Natural Language :: Portuguese (Brazilian)
Classifier: Natural Language :: Romanian
Classifier: Natural Language :: Russian
Classifier: Natural Language :: Serbian
Classifier: Natural Language :: Slovak
Classifier: Natural Language :: Slovenian
Classifier: Natural Language :: Spanish
Classifier: Natural Language :: Swedish
Classifier: Natural Language :: Tamil
Classifier: Natural Language :: Telugu
Classifier: Natural Language :: Thai
Classifier: Natural Language :: Tibetan
Classifier: Natural Language :: Turkish
Classifier: Natural Language :: Ukrainian
Classifier: Natural Language :: Urdu
Classifier: Natural Language :: Vietnamese
Requires-Python: >=3.8,<4
License-File: LICENSE
Requires-Dist: transformers>=4.53.0
Requires-Dist: sentencepiece>=0.1.99
Requires-Dist: bitsandbytes>=0.40.2
Requires-Dist: langcodes>=3.3.0
Requires-Dist: datasets>=2.13.1
Requires-Dist: halo>=0.0.31
Requires-Dist: psutil>=5.9.4
Requires-Dist: shutils>=0.1.0
Requires-Dist: accelerate>=0.20.3
Requires-Dist: questionary>=1.10.0
Requires-Dist: polib>=1.2.0
Dynamic: author
Dynamic: classifier
Dynamic: description
Dynamic: description-content-type
Dynamic: home-page
Dynamic: license
Dynamic: license-file
Dynamic: project-url
Dynamic: requires-dist
Dynamic: requires-python
Dynamic: summary
